{"assets/.DS_Store":["assets/.DS_Store"],"assets/background.jpg":["assets/background.jpg"],"assets/bday.png":["assets/bday.png"],"assets/bg.gif":["assets/bg.gif"],"assets/cloud.png":["assets/cloud.png"],"assets/d.png":["assets/d.png"],"assets/dashrun.png":["assets/dashrun.png"],"assets/dino.png":["assets/dino.png"],"assets/eceb.png":["assets/eceb.png"],"assets/enemy.png":["assets/enemy.png"],"assets/finwithpav.gif":["assets/finwithpav.gif"],"assets/ground.png":["assets/ground.png"],"assets/nowthisisbg.png":["assets/nowthisisbg.png"],"assets/obstacle.png":["assets/obstacle.png"],"assets/optimbg.gif":["assets/optimbg.gif"],"assets/reactobstacle.png":["assets/reactobstacle.png"],"assets/thefin.gif":["assets/thefin.gif"],"assets/vadapav.png":["assets/vadapav.png"],"packages/cupertino_icons/assets/CupertinoIcons.ttf":["packages/cupertino_icons/assets/CupertinoIcons.ttf"]}